ni_python_styleguide/__init__.py
ni_python_styleguide/__main__.py
ni_python_styleguide/_acknowledge_existing_errors/__init__.py
ni_python_styleguide/_cli.py
ni_python_styleguide/_config_constants.py
ni_python_styleguide/_fix.py
ni_python_styleguide/_format.py
ni_python_styleguide/_lint.py
ni_python_styleguide/_utils/__init__.py
ni_python_styleguide/_utils/code_analysis.py
ni_python_styleguide/_utils/lint.py
ni_python_styleguide/_utils/string_helpers.py
ni_python_styleguide/_utils/temp_file.py
ni_python_styleguide/config.ini
ni_python_styleguide/config.toml
ni_python_styleguide-0.4.8.dist-info/LICENSE
ni_python_styleguide-0.4.8.dist-info/METADATA
ni_python_styleguide-0.4.8.dist-info/WHEEL
ni_python_styleguide-0.4.8.dist-info/entry_points.txt
ni_python_styleguide-0.4.8.dist-info/RECORD
