Metadata-Version: 2.1
Name: ni-python-styleguide
Version: 0.4.8
Summary: NI's internal and external Python linter rules and plugins
Home-page: https://github.com/ni/python-styleguide
License: MIT
Author: NI
Author-email: opensource@ni.com
Requires-Python: >=3.7,<4.0
Classifier: License :: OSI Approved :: MIT License
Classifier: Programming Language :: Python :: 3
Classifier: Programming Language :: Python :: 3.7
Classifier: Programming Language :: Python :: 3.8
Classifier: Programming Language :: Python :: 3.9
Classifier: Programming Language :: Python :: 3.10
Classifier: Programming Language :: Python :: 3.11
Classifier: Programming Language :: Python :: 3.12
Requires-Dist: black (>=23.1,<26.0)
Requires-Dist: click (>=7.1.2)
Requires-Dist: flake8 (>=5.0,<6.0) ; python_version >= "3.7" and python_version < "3.12"
Requires-Dist: flake8 (>=6.1,<7.0) ; python_version >= "3.12" and python_version < "4.0"
Requires-Dist: flake8-black (>=0.2.1)
Requires-Dist: flake8-docstrings (>=1.5.0)
Requires-Dist: flake8-import-order (>=0.18.1,<0.19.0)
Requires-Dist: importlib-metadata (<5.0) ; python_version < "3.8"
Requires-Dist: isort (>=5.10)
Requires-Dist: pathspec (>=0.11.1)
Requires-Dist: pep8-naming (>=0.11.1)
Requires-Dist: pycodestyle (>=2.11,<3.0) ; python_version >= "3.12" and python_version < "4.0"
Requires-Dist: pycodestyle (>=2.9,<3.0) ; python_version >= "3.7" and python_version < "3.12"
Requires-Dist: toml (>=0.10.1)
Project-URL: Repository, https://github.com/ni/python-styleguide
